setup.py
open311/__init__.py
open311/open311.py
open311.egg-info/PKG-INFO
open311.egg-info/SOURCES.txt
open311.egg-info/dependency_links.txt
open311.egg-info/top_level.txt
open311/api/__init__.py
open311/api/api.py
open311/api/test_api.py
open311/api/xml2dict/__init__.py
open311/api/xml2dict/object_dict.py
open311/api/xml2dict/xml2dict.py