Metadata-Version: 1.0
Name: open311
Version: 1.1
Summary: A Python API wrapper for the Open311 API v2.
Home-page: https://github.com/codeforamerica/open311_python
Author: Zach Williams
Author-email: zach@codeforamerica.org
License: BSD
Keywords: open311,Open311
Platform: UNKNOWN
Classifier: Development Status :: 5 - Production/Stable
Classifier: Intended Audience :: Developers
Classifier: Natural Language :: English
Classifier: Operating System :: OS Independent
Classifier: Programming Language :: Python :: 2
Classifier: Topic :: Internet
Classifier: Topic :: Internet :: WWW/HTTP
